{
  "headers": {
    "age": "231",
    "alt-svc": "h3=\":443\"; ma=86400",
    "cache-control": "public, max-age=15311",
    "content-type": "application/json;charset=utf-8",
    "etag": "W/\"cd83425ab70664e69eaded542b168097\"",
    "server": "openresty",
    "vary": "accept-encoding, Origin",
    "via": "1.1 0a71d283a25c1e3f082b4dbc9d844dfe.cloudfront.net (CloudFront)",
    "x-amz-cf-id": "3Kw-qwAkN86irGctfA_3O155mFy9YUGan_vZsujVpO3t8ISqUDi41Q==",
    "x-amz-cf-pop": "FRA60-P3",
    "x-az": "us-east-1a",
    "x-cache": "Hit from cloudfront",
    "x-memc": "HIT",
    "x-memc-age": "11472",
    "x-memc-expires": "15311",
    "x-memc-key": "6fcfbaac03aa829867b3000b079e1294",
    "x-task-id": "283fac73c39b44e1aa291ef328a8fc79"
  },
  "data": {
    "_id": "52570ebe19c295711402beef",
    "air_date": "1988-12-31",
    "episodes": [
      {
        "air_date": "1988-12-31",
        "episode_number": 1,
        "episode_type": "standard",
        "id": 85865,
        "name": "Polite Mollusk",
        "overview": "Conculco consequuntur ratione. Dolor aequitas celo cotidie amissio molestiae commodo venio cernuus. Tepidus surgo comitatus tempora.",
        "production_code": "",
        "runtime": 60,
        "season_number": 0,
        "show_id": 1636,
        "still_path": null,
        "vote_average": 0,
        "vote_count": 0,
        "crew": [],
        "guest_stars": [
          {
            "character": "Presenter",
            "credit_id": "6386553a3d35570096dc7893",
            "order": 685,
            "adult": false,
            "gender": 2,
            "id": 1965711,
            "known_for_department": "Acting",
            "name": "Maxine Keeling",
            "original_name": "Maxine Keeling",
            "popularity": 0.4471,
            "profile_path": null
          },
          {
            "character": "Presenter",
            "credit_id": "6386554d2e06970245e7dba9",
            "order": 686,
            "adult": false,
            "gender": 0,
            "id": 1226244,
            "known_for_department": "Acting",
            "name": "Celia Franey Jr.",
            "original_name": "Celia Franey Jr.",
            "popularity": 0.8207,
            "profile_path": null
          },
          {
            "character": "Presenter",
            "credit_id": "6386556e229ae21572aa09a7",
            "order": 687,
            "adult": false,
            "gender": 2,
            "id": 1108271,
            "known_for_department": "Acting",
            "name": "Mr. Bruce Gusikowski",
            "original_name": "Mr. Bruce Gusikowski",
            "popularity": 0.6449,
            "profile_path": "/mERVNAdGaxoUvzy9SYuAvqjtZke.jpg"
          },
          {
            "character": "Presenter",
            "credit_id": "63865581fb83460087713584",
            "order": 688,
            "adult": false,
            "gender": 2,
            "id": 231557,
            "known_for_department": "Acting",
            "name": "Stephanie Crooks",
            "original_name": "Stephanie Crooks",
            "popularity": 1.1833,
            "profile_path": "/eWPle9BWx0iljiViQ0CRdx9g6ww.jpg"
          },
          {
            "character": "Presenter",
            "credit_id": "638655e03d3557007fc5c50a",
            "order": 689,
            "adult": false,
            "gender": 0,
            "id": 1996163,
            "known_for_department": "Acting",
            "name": "Hugh Brown",
            "original_name": "Hugh Brown",
            "popularity": 0.7368,
            "profile_path": "/c8zEebf9SEZLCCWC4BHKCnD4GOK.jpg"
          },
          {
            "character": "Presenter",
            "credit_id": "6386560ca410c8008cd5964b",
            "order": 690,
            "adult": false,
            "gender": 0,
            "id": 1217441,
            "known_for_department": "Acting",
            "name": "Fredrick Lesch",
            "original_name": "Fredrick Lesch",
            "popularity": 0.4046,
            "profile_path": null
          },
          {
            "character": "Presenter",
            "credit_id": "638656245ed8e900ca724199",
            "order": 691,
            "adult": false,
            "gender": 2,
            "id": 1247295,
            "known_for_department": "Acting",
            "name": "Lonnie Dickinson",
            "original_name": "Lonnie Dickinson",
            "popularity": 0.3148,
            "profile_path": "/1iCXWISg9B5gsGDkwpIq0bDfUFB.jpg"
          },
          {
            "character": "Presenter",
            "credit_id": "638656521b157d008245f404",
            "order": 692,
            "adult": false,
            "gender": 0,
            "id": 1226236,
            "known_for_department": "Acting",
            "name": "Alma Windler IV",
            "original_name": "Alma Windler IV",
            "popularity": 0.3808,
            "profile_path": "/e9w44oOlt8hyaAL85KDxNfdhSZu.jpg"
          },
          {
            "character": "Presenter",
            "credit_id": "638656692e06970245e7dbf5",
            "order": 693,
            "adult": false,
            "gender": 2,
            "id": 1220465,
            "known_for_department": "Acting",
            "name": "Lester Rogahn Sr.",
            "original_name": "Lester Rogahn Sr.",
            "popularity": 1.0983,
            "profile_path": "/e5XXc18U4I9g2z4Sh81t3wEFfHa.jpg"
          },
          {
            "character": "Presenter",
            "credit_id": "638656893d35570079651d62",
            "order": 694,
            "adult": false,
            "gender": 2,
            "id": 1212720,
            "known_for_department": "Acting",
            "name": "Andre Lockman",
            "original_name": "Andre Lockman",
            "popularity": 0.5521,
            "profile_path": "/cCD1gBmMn2RK56nwB0STw6mu8KZ.jpg"
          },
          {
            "character": "Presenter",
            "credit_id": "638656a4229ae21572aa0a07",
            "order": 695,
            "adult": false,
            "gender": 2,
            "id": 1053440,
            "known_for_department": "Acting",
            "name": "Forrest Schowalter",
            "original_name": "Forrest Schowalter",
            "popularity": 1.7396,
            "profile_path": "/28KmXueehUDy8CdXB6q9zYugd2G.jpg"
          },
          {
            "character": "Presenter",
            "credit_id": "638656cd3d3557008407134d",
            "order": 696,
            "adult": false,
            "gender": 2,
            "id": 1216057,
            "known_for_department": "Acting",
            "name": "Micheal Turner",
            "original_name": "Micheal Turner",
            "popularity": 0.838,
            "profile_path": "/2RcuAa1nWjXOUemem2s7PJpKoye.jpg"
          },
          {
            "character": "Presenter",
            "credit_id": "638656ee229ae21572aa0a15",
            "order": 697,
            "adult": false,
            "gender": 2,
            "id": 1684245,
            "known_for_department": "Acting",
            "name": "Edna Kub",
            "original_name": "Edna Kub",
            "popularity": 0.3172,
            "profile_path": null
          },
          {
            "character": "",
            "credit_id": "642812f0a3e4ba00b4239dc8",
            "order": 709,
            "adult": false,
            "gender": 1,
            "id": 3125,
            "known_for_department": "Acting",
            "name": "Stuart Muller I",
            "original_name": "Stuart Muller I",
            "popularity": 4.7868,
            "profile_path": "/8XtGxpB4z428QDgwKlFYPktYHFC.jpg"
          },
          {
            "character": "",
            "credit_id": "6444ee49b3f6f505269f0bc2",
            "order": 718,
            "adult": false,
            "gender": 2,
            "id": 11370,
            "known_for_department": "Acting",
            "name": "Phillip Lehner",
            "original_name": "Phillip Lehner",
            "popularity": 1.2976,
            "profile_path": "/9G3k29OWPyZtScEDZEAsFJpqiM7.jpg"
          },
          {
            "character": "",
            "credit_id": "66a62f76afacfa4dfbb4f237",
            "order": 809,
            "adult": false,
            "gender": 2,
            "id": 10592,
            "known_for_department": "Acting",
            "name": "Dr. Alton Jacobson",
            "original_name": "Dr. Alton Jacobson",
            "popularity": 3.1229,
            "profile_path": "/iawyLGZKTr7eD8XWhNGjM8Cb95x.jpg"
          },
          {
            "character": "",
            "credit_id": "67310b9c5380ee7a0d6488f9",
            "order": 967,
            "adult": false,
            "gender": 2,
            "id": 22868,
            "known_for_department": "Acting",
            "name": "Wallace Okuneva",
            "original_name": "Wallace Okuneva",
            "popularity": 1.8745,
            "profile_path": "/15zBIv3qhHj5vXwWOFl4ZfDb2bO.jpg"
          },
          {
            "character": "",
            "credit_id": "67310bea55ba94681fbd4b5f",
            "order": 968,
            "adult": false,
            "gender": 2,
            "id": 3284,
            "known_for_department": "Acting",
            "name": "Roland Stoltenberg",
            "original_name": "Roland Stoltenberg",
            "popularity": 2.7705,
            "profile_path": "/et5hx6xJRnquGgEHGshmiAZZwgN.jpg"
          },
          {
            "character": "",
            "credit_id": "67310bf4d2352682d920a5df",
            "order": 969,
            "adult": false,
            "gender": 1,
            "id": 1226069,
            "known_for_department": "Acting",
            "name": "Everett Farrell",
            "original_name": "Everett Farrell",
            "popularity": 0.9682,
            "profile_path": "/nHVSWjYPErPWFyD6c7Nz1GdaqiG.jpg"
          },
          {
            "character": "",
            "credit_id": "67310c1a55ba94681fbd4b88",
            "order": 970,
            "adult": false,
            "gender": 1,
            "id": 193492,
            "known_for_department": "Acting",
            "name": "Ronnie Heidenreich",
            "original_name": "Ronnie Heidenreich",
            "popularity": 1.4383,
            "profile_path": "/64WXUHwvOpcxzN9eQXxnsoO4bIB.jpg"
          },
          {
            "character": "",
            "credit_id": "67310c2f6520546689f4f597",
            "order": 971,
            "adult": false,
            "gender": 2,
            "id": 1428,
            "known_for_department": "Acting",
            "name": "Joseph Luettgen",
            "original_name": "Joseph Luettgen",
            "popularity": 3.7274,
            "profile_path": "/r1uFIYnBCDhIlqNbiTS4nDrjHrl.jpg"
          }
        ]
      },
      {
        "air_date": null,
        "episode_number": 2,
        "episode_type": "standard",
        "id": 4972346,
        "name": "Magnetic Mollusk",
        "overview": "",
        "production_code": "",
        "runtime": null,
        "season_number": 0,
        "show_id": 1636,
        "still_path": null,
        "vote_average": 0,
        "vote_count": 0,
        "crew": [],
        "guest_stars": []
      },
      {
        "air_date": null,
        "episode_number": 3,
        "episode_type": "standard",
        "id": 4972347,
        "name": "Live Pinniped",
        "overview": "",
        "production_code": "",
        "runtime": null,
        "season_number": 0,
        "show_id": 1636,
        "still_path": null,
        "vote_average": 0,
        "vote_count": 0,
        "crew": [],
        "guest_stars": []
      },
      {
        "air_date": "1978-12-25",
        "episode_number": 15,
        "episode_type": "standard",
        "id": 3408582,
        "name": "Brainy Planarian",
        "overview": "Aliquid approbo quos sol alienus uxor laboriosam. Ventosus cenaculum enim arceo corrumpo avarus ultio similique vobis.",
        "production_code": "",
        "runtime": 60,
        "season_number": 0,
        "show_id": 1636,
        "still_path": null,
        "vote_average": 0,
        "vote_count": 0,
        "crew": [],
        "guest_stars": []
      },
      {
        "air_date": "1980-12-25",
        "episode_number": 17,
        "episode_type": "standard",
        "id": 85866,
        "name": "Beautiful Parrot",
        "overview": "Alveus theologus contra.",
        "production_code": "",
        "runtime": 60,
        "season_number": 0,
        "show_id": 1636,
        "still_path": null,
        "vote_average": 0,
        "vote_count": 0,
        "crew": [],
        "guest_stars": []
      },
      {
        "air_date": "1981-12-25",
        "episode_number": 18,
        "episode_type": "standard",
        "id": 85867,
        "name": "Mechanical Sheep",
        "overview": "Dedico vorago suasoria voco cribro claustrum modi degero. Cruentus beneficium voluptate capio voluptates aperiam coerceo. Complectus argentum fugiat.",
        "production_code": "",
        "runtime": 60,
        "season_number": 0,
        "show_id": 1636,
        "still_path": null,
        "vote_average": 0,
        "vote_count": 0,
        "crew": [],
        "guest_stars": []
      },
      {
        "air_date": "1982-12-25",
        "episode_number": 19,
        "episode_type": "standard",
        "id": 85868,
        "name": "Biological Cephalopod",
        "overview": "Uterque adfectus voluptatibus temeritas magni. Deprecator vulpes animus ager quibusdam vesco succedo cognomen comes ratione. Centum creber thesis.",
        "production_code": "",
        "runtime": 60,
        "season_number": 0,
        "show_id": 1636,
        "still_path": null,
        "vote_average": 0,
        "vote_count": 0,
        "crew": [],
        "guest_stars": []
      },
      {
        "air_date": "1983-12-25",
        "episode_number": 20,
        "episode_type": "standard",
        "id": 85869,
        "name": "Local Thrush",
        "overview": "Adaugeo capto quia rerum delego nam voluntarius vallum commodi. Cilicium atqui balbus antea defetiscor aliquam cunabula. Veritatis tersus asporto.",
        "production_code": "",
        "runtime": 60,
        "season_number": 0,
        "show_id": 1636,
        "still_path": null,
        "vote_average": 0,
        "vote_count": 0,
        "crew": [],
        "guest_stars": []
      },
      {
        "air_date": "1984-12-25",
        "episode_number": 21,
        "episode_type": "standard",
        "id": 85870,
        "name": "Glorious Octopus",
        "overview": "Aspernatur socius beatus amitto acerbitas. Tabgo curis sumptus volva adinventitias commodi solio victoria attollo error.",
        "production_code": "",
        "runtime": 60,
        "season_number": 0,
        "show_id": 1636,
        "still_path": null,
        "vote_average": 0,
        "vote_count": 0,
        "crew": [],
        "guest_stars": []
      },
      {
        "air_date": "1985-12-25",
        "episode_number": 22,
        "episode_type": "standard",
        "id": 85871,
        "name": "Rival Wombat",
        "overview": "Spargo utroque veritas desipio utrum curto.",
        "production_code": "",
        "runtime": 60,
        "season_number": 0,
        "show_id": 1636,
        "still_path": null,
        "vote_average": 0,
        "vote_count": 0,
        "crew": [],
        "guest_stars": []
      },
      {
        "air_date": "1986-12-25",
        "episode_number": 23,
        "episode_type": "standard",
        "id": 85872,
        "name": "Absent Cockroach",
        "overview": "Nihil copiose absum venustas ubi strenuus ambitus sopor unus. Ait tego sum crepusculum.",
        "production_code": "",
        "runtime": 60,
        "season_number": 0,
        "show_id": 1636,
        "still_path": null,
        "vote_average": 0,
        "vote_count": 0,
        "crew": [],
        "guest_stars": []
      },
      {
        "air_date": "1987-12-25",
        "episode_number": 24,
        "episode_type": "standard",
        "id": 85873,
        "name": "Costly Flamingo",
        "overview": "Agnitio vaco ratione defetiscor infit. Utique architecto bellum antiquus admoveo caritas demo textilis. Universe comis vorago cruciamentum.",
        "production_code": "",
        "runtime": 60,
        "season_number": 0,
        "show_id": 1636,
        "still_path": null,
        "vote_average": 0,
        "vote_count": 0,
        "crew": [],
        "guest_stars": []
      },
      {
        "air_date": "1988-12-25",
        "episode_number": 25,
        "episode_type": "standard",
        "id": 85874,
        "name": "Fiscal Canid",
        "overview": "Thymbra delectus solvo cubo aut conicio tamquam. Vita tabesco assumenda suffragium vestrum coniuratio numquam.",
        "production_code": "",
        "runtime": 60,
        "season_number": 0,
        "show_id": 1636,
        "still_path": null,
        "vote_average": 0,
        "vote_count": 0,
        "crew": [],
        "guest_stars": []
      },
      {
        "air_date": "1989-12-25",
        "episode_number": 26,
        "episode_type": "standard",
        "id": 85875,
        "name": "Mechanical Slug",
        "overview": "Valens illum pauper copia desino altus canto cum callide vesco. Vesco copia libero quo magni. Ipsa abbas tamdiu tamquam chirographum summisse desino calamitas terreo.",
        "production_code": "",
        "runtime": 60,
        "season_number": 0,
        "show_id": 1636,
        "still_path": null,
        "vote_average": 0,
        "vote_count": 0,
        "crew": [],
        "guest_stars": []
      },
      {
        "air_date": null,
        "episode_number": 27,
        "episode_type": "standard",
        "id": 85876,
        "name": "Spiritual Viper",
        "overview": "",
        "production_code": "",
        "runtime": 60,
        "season_number": 0,
        "show_id": 1636,
        "still_path": null,
        "vote_average": 0,
        "vote_count": 0,
        "crew": [],
        "guest_stars": []
      },
      {
        "air_date": "1984-12-27",
        "episode_number": 29,
        "episode_type": "standard",
        "id": 85877,
        "name": "Full Lungfish",
        "overview": "Auditor color denuncio coepi adinventitias tamquam. Coma adaugeo tersus.",
        "production_code": "",
        "runtime": 60,
        "season_number": 0,
        "show_id": 1636,
        "still_path": null,
        "vote_average": 0,
        "vote_count": 0,
        "crew": [],
        "guest_stars": []
      },
      {
        "air_date": "2019-12-25",
        "episode_number": 30,
        "episode_type": "standard",
        "id": 2192029,
        "name": "Organic Turkey",
        "overview": "Sponte vae tondeo sophismata tactus candidus viduo complectus. Decor agnosco averto cuppedia terebro cometes. Exercitationem deleo taceo utroque.",
        "production_code": "",
        "runtime": 60,
        "season_number": 0,
        "show_id": 1636,
        "still_path": null,
        "vote_average": 0,
        "vote_count": 0,
        "crew": [],
        "guest_stars": [
          {
            "character": "Presenter",
            "credit_id": "63865761229ae2158117b114",
            "order": 698,
            "adult": false,
            "gender": 1,
            "id": 1216060,
            "known_for_department": "Acting",
            "name": "Nick Deckow",
            "original_name": "Nick Deckow",
            "popularity": 1.4489,
            "profile_path": "/vmmNALj0tR9ZzmV8FmykQ00QnxF.jpg"
          },
          {
            "character": "Presenter",
            "credit_id": "63865775fb8346008441db26",
            "order": 699,
            "adult": false,
            "gender": 1,
            "id": 2215732,
            "known_for_department": "Acting",
            "name": "Lana Hettinger",
            "original_name": "Lana Hettinger",
            "popularity": 0.7834,
            "profile_path": "/f5XikaqOSgsM8wd1y3Nca7SGzYM.jpg"
          }
        ]
      },
      {
        "air_date": "1989-12-28",
        "episode_number": 31,
        "episode_type": "standard",
        "id": 2373078,
        "name": "Unknown Bug",
        "overview": "Delego coma derelinquo.",
        "production_code": "",
        "runtime": 59,
        "season_number": 0,
        "show_id": 1636,
        "still_path": null,
        "vote_average": 0,
        "vote_count": 0,
        "crew": [
          {
            "job": "Presenter",
            "department": "Crew",
            "credit_id": "63ba8d38f8595800ae325e65",
            "adult": false,
            "gender": 2,
            "id": 1212720,
            "known_for_department": "Acting",
            "name": "Andre Lockman",
            "original_name": "Andre Lockman",
            "popularity": 0.5521,
            "profile_path": "/cCD1gBmMn2RK56nwB0STw6mu8KZ.jpg"
          },
          {
            "job": "Presenter",
            "department": "Crew",
            "credit_id": "63ba90b5a6e2d20083e14841",
            "adult": false,
            "gender": 2,
            "id": 1053440,
            "known_for_department": "Acting",
            "name": "Forrest Schowalter",
            "original_name": "Forrest Schowalter",
            "popularity": 1.7396,
            "profile_path": "/28KmXueehUDy8CdXB6q9zYugd2G.jpg"
          }
        ],
        "guest_stars": [
          {
            "character": "Self",
            "credit_id": "52570f1519c2957114030eb9",
            "order": 550,
            "adult": false,
            "gender": 2,
            "id": 110001,
            "known_for_department": "Acting",
            "name": "Guadalupe Lind",
            "original_name": "Guadalupe Lind",
            "popularity": 3.1676,
            "profile_path": "/zbIUgUJ4j2AOUerDoeOTWCvx9P2.jpg"
          },
          {
            "character": "Self",
            "credit_id": "61f65838dcf87500ed70c408",
            "order": 648,
            "adult": false,
            "gender": 2,
            "id": 1155529,
            "known_for_department": "Acting",
            "name": "Dr. Shannon Wehner",
            "original_name": "Dr. Shannon Wehner",
            "popularity": 0.9277,
            "profile_path": "/fsWAD5muDvcWYGGctdHupkzXJ3x.jpg"
          },
          {
            "character": "",
            "credit_id": "63ba8fe1fa4046008755adfa",
            "order": 706,
            "adult": false,
            "gender": 1,
            "id": 1189943,
            "known_for_department": "Acting",
            "name": "Ray Hermann",
            "original_name": "Ray Hermann",
            "popularity": 1.0202,
            "profile_path": "/95Kln9WJAADpNNexJJnwYLWfy9f.jpg"
          },
          {
            "character": "",
            "credit_id": "63ba8fedfc31d3007e3157a9",
            "order": 707,
            "adult": false,
            "gender": 0,
            "id": 3858387,
            "known_for_department": "Acting",
            "name": "Mercedes Kunze",
            "original_name": "Mercedes Kunze",
            "popularity": 0.0633,
            "profile_path": null
          },
          {
            "character": "Self",
            "credit_id": "6731f4940447470da614a20a",
            "order": 973,
            "adult": false,
            "gender": 2,
            "id": 1224916,
            "known_for_department": "Acting",
            "name": "Carmen Krajcik Jr.",
            "original_name": "Carmen Krajcik Jr.",
            "popularity": 1.2042,
            "profile_path": "/3LwyDjtLARNX46kydi0Nf9gD8U6.jpg"
          }
        ]
      },
      {
        "air_date": null,
        "episode_number": 32,
        "episode_type": "standard",
        "id": 3314289,
        "name": "Injured Trout",
        "overview": "",
        "production_code": "",
        "runtime": 60,
        "season_number": 0,
        "show_id": 1636,
        "still_path": null,
        "vote_average": 0,
        "vote_count": 0,
        "crew": [],
        "guest_stars": []
      },
      {
        "air_date": "1998-12-03",
        "episode_number": 33,
        "episode_type": "standard",
        "id": 3314290,
        "name": "Flying Beaver",
        "overview": "Tepesco atavus cohibeo ago coniuratio dens theologus.",
        "production_code": "",
        "runtime": 60,
        "season_number": 0,
        "show_id": 1636,
        "still_path": null,
        "vote_average": 0,
        "vote_count": 0,
        "crew": [],
        "guest_stars": []
      },
      {
        "air_date": null,
        "episode_number": 100,
        "episode_type": "standard",
        "id": 3314260,
        "name": "Reasonable Prawn",
        "overview": "",
        "production_code": "",
        "runtime": 60,
        "season_number": 0,
        "show_id": 1636,
        "still_path": null,
        "vote_average": 0,
        "vote_count": 0,
        "crew": [],
        "guest_stars": []
      },
      {
        "air_date": null,
        "episode_number": 102,
        "episode_type": "standard",
        "id": 3314261,
        "name": "Rude Bedbug",
        "overview": "",
        "production_code": "",
        "runtime": 60,
        "season_number": 0,
        "show_id": 1636,
        "still_path": null,
        "vote_average": 0,
        "vote_count": 0,
        "crew": [],
        "guest_stars": []
      },
      {
        "air_date": null,
        "episode_number": 103,
        "episode_type": "standard",
        "id": 3314262,
        "name": "Xeric Wildebeest",
        "overview": "",
        "production_code": "",
        "runtime": 60,
        "season_number": 0,
        "show_id": 1636,
        "still_path": null,
        "vote_average": 0,
        "vote_count": 0,
        "crew": [],
        "guest_stars": []
      },
      {
        "air_date": null,
        "episode_number": 104,
        "episode_type": "standard",
        "id": 3314263,
        "name": "Reluctant Starfish",
        "overview": "",
        "production_code": "",
        "runtime": 60,
        "season_number": 0,
        "show_id": 1636,
        "still_path": null,
        "vote_average": 0,
        "vote_count": 0,
        "crew": [],
        "guest_stars": []
      },
      {
        "air_date": null,
        "episode_number": 105,
        "episode_type": "standard",
        "id": 3314264,
        "name": "Ministerial Elk",
        "overview": "",
        "production_code": "",
        "runtime": 60,
        "season_number": 0,
        "show_id": 1636,
        "still_path": null,
        "vote_average": 0,
        "vote_count": 0,
        "crew": [],
        "guest_stars": []
      },
      {
        "air_date": null,
        "episode_number": 106,
        "episode_type": "standard",
        "id": 3314265,
        "name": "Wittering Fox",
        "overview": "",
        "production_code": "",
        "runtime": 60,
        "season_number": 0,
        "show_id": 1636,
        "still_path": null,
        "vote_average": 0,
        "vote_count": 0,
        "crew": [],
        "guest_stars": []
      },
      {
        "air_date": null,
        "episode_number": 107,
        "episode_type": "standard",
        "id": 3314266,
        "name": "Ready Dormouse",
        "overview": "",
        "production_code": "",
        "runtime": 60,
        "season_number": 0,
        "show_id": 1636,
        "still_path": null,
        "vote_average": 0,
        "vote_count": 0,
        "crew": [],
        "guest_stars": []
      },
      {
        "air_date": null,
        "episode_number": 108,
        "episode_type": "standard",
        "id": 3314267,
        "name": "Encouraging Dog",
        "overview": "",
        "production_code": "",
        "runtime": 60,
        "season_number": 0,
        "show_id": 1636,
        "still_path": null,
        "vote_average": 0,
        "vote_count": 0,
        "crew": [],
        "guest_stars": []
      },
      {
        "air_date": null,
        "episode_number": 109,
        "episode_type": "standard",
        "id": 3314268,
        "name": "Variable Guanaco",
        "overview": "",
        "production_code": "",
        "runtime": 60,
        "season_number": 0,
        "show_id": 1636,
        "still_path": null,
        "vote_average": 0,
        "vote_count": 0,
        "crew": [],
        "guest_stars": []
      },
      {
        "air_date": null,
        "episode_number": 110,
        "episode_type": "standard",
        "id": 3314269,
        "name": "Optimistic Crayfish",
        "overview": "",
        "production_code": "",
        "runtime": 60,
        "season_number": 0,
        "show_id": 1636,
        "still_path": null,
        "vote_average": 0,
        "vote_count": 0,
        "crew": [],
        "guest_stars": []
      },
      {
        "air_date": null,
        "episode_number": 111,
        "episode_type": "standard",
        "id": 3314270,
        "name": "Loose Hare",
        "overview": "",
        "production_code": "",
        "runtime": 60,
        "season_number": 0,
        "show_id": 1636,
        "still_path": null,
        "vote_average": 0,
        "vote_count": 0,
        "crew": [],
        "guest_stars": []
      },
      {
        "air_date": null,
        "episode_number": 112,
        "episode_type": "standard",
        "id": 3314271,
        "name": "Rear Bison",
        "overview": "",
        "production_code": "",
        "runtime": 60,
        "season_number": 0,
        "show_id": 1636,
        "still_path": null,
        "vote_average": 0,
        "vote_count": 0,
        "crew": [],
        "guest_stars": []
      },
      {
        "air_date": null,
        "episode_number": 113,
        "episode_type": "standard",
        "id": 3314272,
        "name": "Burning Magpie",
        "overview": "",
        "production_code": "",
        "runtime": 60,
        "season_number": 0,
        "show_id": 1636,
        "still_path": null,
        "vote_average": 0,
        "vote_count": 0,
        "crew": [],
        "guest_stars": []
      },
      {
        "air_date": null,
        "episode_number": 114,
        "episode_type": "standard",
        "id": 3314273,
        "name": "Strange Rhinoceros",
        "overview": "",
        "production_code": "",
        "runtime": 60,
        "season_number": 0,
        "show_id": 1636,
        "still_path": null,
        "vote_average": 0,
        "vote_count": 0,
        "crew": [],
        "guest_stars": []
      },
      {
        "air_date": null,
        "episode_number": 115,
        "episode_type": "standard",
        "id": 3314274,
        "name": "Residential Whitefish",
        "overview": "",
        "production_code": "",
        "runtime": 60,
        "season_number": 0,
        "show_id": 1636,
        "still_path": null,
        "vote_average": 0,
        "vote_count": 0,
        "crew": [],
        "guest_stars": []
      },
      {
        "air_date": null,
        "episode_number": 116,
        "episode_type": "standard",
        "id": 3314275,
        "name": "Zygotic Wren",
        "overview": "",
        "production_code": "",
        "runtime": 60,
        "season_number": 0,
        "show_id": 1636,
        "still_path": null,
        "vote_average": 0,
        "vote_count": 0,
        "crew": [],
        "guest_stars": []
      },
      {
        "air_date": null,
        "episode_number": 117,
        "episode_type": "standard",
        "id": 3314276,
        "name": "Early Marlin",
        "overview": "",
        "production_code": "",
        "runtime": 60,
        "season_number": 0,
        "show_id": 1636,
        "still_path": null,
        "vote_average": 0,
        "vote_count": 0,
        "crew": [],
        "guest_stars": []
      },
      {
        "air_date": "2018-01-05",
        "episode_number": 118,
        "episode_type": "standard",
        "id": 3314277,
        "name": "Spatial Lizard",
        "overview": "Expedita apostolus debeo summisse defungo abutor uterque congregatio pax. Delicate adipiscor auctus suscipit exercitationem decimus. Facere cunabula quaerat cur degusto arcus supra blandior.",
        "production_code": "",
        "runtime": 59,
        "season_number": 0,
        "show_id": 1636,
        "still_path": null,
        "vote_average": 0,
        "vote_count": 0,
        "crew": [],
        "guest_stars": []
      },
      {
        "air_date": "2018-01-05",
        "episode_number": 119,
        "episode_type": "standard",
        "id": 3314278,
        "name": "Circular Cardinal",
        "overview": "Ter cohors trans capto spoliatio vulgivagus casus demulceo demo. Adsuesco deorsum communis. Deleo veritatis ventito calcar tersus peccatus curriculum curis.",
        "production_code": "",
        "runtime": 59,
        "season_number": 0,
        "show_id": 1636,
        "still_path": null,
        "vote_average": 9,
        "vote_count": 1,
        "crew": [],
        "guest_stars": []
      },
      {
        "air_date": null,
        "episode_number": 120,
        "episode_type": "standard",
        "id": 3314279,
        "name": "Famous Guanaco",
        "overview": "",
        "production_code": "",
        "runtime": 60,
        "season_number": 0,
        "show_id": 1636,
        "still_path": null,
        "vote_average": 0,
        "vote_count": 0,
        "crew": [],
        "guest_stars": []
      },
      {
        "air_date": null,
        "episode_number": 121,
        "episode_type": "standard",
        "id": 3314280,
        "name": "Silky Badger",
        "overview": "",
        "production_code": "",
        "runtime": 60,
        "season_number": 0,
        "show_id": 1636,
        "still_path": null,
        "vote_average": 0,
        "vote_count": 0,
        "crew": [],
        "guest_stars": []
      },
      {
        "air_date": null,
        "episode_number": 122,
        "episode_type": "standard",
        "id": 3314281,
        "name": "Inquisitive Meadowlark",
        "overview": "",
        "production_code": "",
        "runtime": 60,
        "season_number": 0,
        "show_id": 1636,
        "still_path": null,
        "vote_average": 0,
        "vote_count": 0,
        "crew": [],
        "guest_stars": []
      },
      {
        "air_date": "2019-01-04",
        "episode_number": 123,
        "episode_type": "standard",
        "id": 3314282,
        "name": "Complex Koala",
        "overview": "Corroboro vilis abundans usque depulso voluptate canto.",
        "production_code": "",
        "runtime": 28,
        "season_number": 0,
        "show_id": 1636,
        "still_path": null,
        "vote_average": 0,
        "vote_count": 0,
        "crew": [],
        "guest_stars": []
      },
      {
        "air_date": "2019-06-07",
        "episode_number": 124,
        "episode_type": "standard",
        "id": 3314283,
        "name": "Exuberant Turtle",
        "overview": "Sollers curia eum tristis creber illo. Demum minus voco error vito aufero cogo blanditiis cito adimpleo.",
        "production_code": "",
        "runtime": 59,
        "season_number": 0,
        "show_id": 1636,
        "still_path": null,
        "vote_average": 8,
        "vote_count": 1,
        "crew": [],
        "guest_stars": []
      },
      {
        "air_date": "2019-06-07",
        "episode_number": 125,
        "episode_type": "standard",
        "id": 3314284,
        "name": "Conservative Parakeet",
        "overview": "Sollers aegrus terra. Bellicus verbum tamen callide absque color quas consequatur tergiversatio sono. Amplus accendo deprimo accommodo armarium thesis arca vulpes.",
        "production_code": "",
        "runtime": 59,
        "season_number": 0,
        "show_id": 1636,
        "still_path": null,
        "vote_average": 8,
        "vote_count": 1,
        "crew": [],
        "guest_stars": []
      },
      {
        "air_date": null,
        "episode_number": 126,
        "episode_type": "standard",
        "id": 3314285,
        "name": "Vicious Crow",
        "overview": "",
        "production_code": "",
        "runtime": 60,
        "season_number": 0,
        "show_id": 1636,
        "still_path": null,
        "vote_average": 0,
        "vote_count": 0,
        "crew": [],
        "guest_stars": []
      },
      {
        "air_date": null,
        "episode_number": 127,
        "episode_type": "standard",
        "id": 3314286,
        "name": "Grumpy Perch",
        "overview": "",
        "production_code": "",
        "runtime": 60,
        "season_number": 0,
        "show_id": 1636,
        "still_path": null,
        "vote_average": 0,
        "vote_count": 0,
        "crew": [],
        "guest_stars": []
      },
      {
        "air_date": null,
        "episode_number": 128,
        "episode_type": "standard",
        "id": 3314287,
        "name": "Mass Aardvark",
        "overview": "",
        "production_code": "",
        "runtime": 60,
        "season_number": 0,
        "show_id": 1636,
        "still_path": null,
        "vote_average": 0,
        "vote_count": 0,
        "crew": [],
        "guest_stars": []
      },
      {
        "air_date": null,
        "episode_number": 129,
        "episode_type": "standard",
        "id": 3314288,
        "name": "Vocational Elephant",
        "overview": "",
        "production_code": "",
        "runtime": 60,
        "season_number": 0,
        "show_id": 1636,
        "still_path": null,
        "vote_average": 0,
        "vote_count": 0,
        "crew": [],
        "guest_stars": []
      },
      {
        "air_date": "2022-03-12",
        "episode_number": 130,
        "episode_type": "standard",
        "id": 3621409,
        "name": "Eastern Frog",
        "overview": "Uxor candidus creo delibero peccatus candidus spiculum patruus amplexus. Vesper minus autem confido advoco.",
        "production_code": "",
        "runtime": 60,
        "season_number": 0,
        "show_id": 1636,
        "still_path": null,
        "vote_average": 0,
        "vote_count": 0,
        "crew": [],
        "guest_stars": []
      },
      {
        "air_date": "2022-03-12",
        "episode_number": 131,
        "episode_type": "standard",
        "id": 3621410,
        "name": "Profitable Chickadee",
        "overview": "Calcar accendo contra.",
        "production_code": "",
        "runtime": 60,
        "season_number": 0,
        "show_id": 1636,
        "still_path": null,
        "vote_average": 0,
        "vote_count": 0,
        "crew": [],
        "guest_stars": []
      },
      {
        "air_date": "2022-03-19",
        "episode_number": 132,
        "episode_type": "standard",
        "id": 3621411,
        "name": "Cooperative Rooster",
        "overview": "Sustineo copiose ager expedita toties. Aegrotatio desolo aspicio atrox tergiversatio cotidie conscendo. Undique sodalitas damnatio arca.",
        "production_code": "",
        "runtime": 60,
        "season_number": 0,
        "show_id": 1636,
        "still_path": null,
        "vote_average": 0,
        "vote_count": 0,
        "crew": [],
        "guest_stars": []
      },
      {
        "air_date": "2022-03-19",
        "episode_number": 133,
        "episode_type": "standard",
        "id": 3621412,
        "name": "Quiet Cougar",
        "overview": "Calculus sed praesentium dedico valetudo. Decet verto caveo cattus carus venustas strenuus cognomen. Caute aureus alioqui varius advoco.",
        "production_code": "",
        "runtime": 60,
        "season_number": 0,
        "show_id": 1636,
        "still_path": null,
        "vote_average": 0,
        "vote_count": 0,
        "crew": [],
        "guest_stars": []
      },
      {
        "air_date": "2022-03-20",
        "episode_number": 134,
        "episode_type": "standard",
        "id": 3662751,
        "name": "Equal Wallaby",
        "overview": "Virga acquiro utpote. Barba quibusdam depopulo utique virgo sumo.",
        "production_code": "",
        "runtime": 59,
        "season_number": 0,
        "show_id": 1636,
        "still_path": null,
        "vote_average": 0,
        "vote_count": 0,
        "crew": [],
        "guest_stars": []
      },
      {
        "air_date": "2022-04-02",
        "episode_number": 135,
        "episode_type": "standard",
        "id": 3662752,
        "name": "Resident Goose",
        "overview": "Depromo sono quos sumptus tum vobis. Libero cursim defero omnis assumenda spero uxor dens vicinus.",
        "production_code": "",
        "runtime": 59,
        "season_number": 0,
        "show_id": 1636,
        "still_path": null,
        "vote_average": 0,
        "vote_count": 0,
        "crew": [],
        "guest_stars": []
      },
      {
        "air_date": "2022-04-09",
        "episode_number": 136,
        "episode_type": "standard",
        "id": 3662753,
        "name": "Misty Reindeer",
        "overview": "Depromo taceo vorago caterva vesper corrupti sint subseco surgo undique.",
        "production_code": "",
        "runtime": 60,
        "season_number": 0,
        "show_id": 1636,
        "still_path": null,
        "vote_average": 0,
        "vote_count": 0,
        "crew": [],
        "guest_stars": []
      },
      {
        "air_date": "2022-04-09",
        "episode_number": 137,
        "episode_type": "standard",
        "id": 3662754,
        "name": "Chronic Camel",
        "overview": "Armarium vespillo eum degero tubineus umbra. Spes coruscus tendo.",
        "production_code": "",
        "runtime": 59,
        "season_number": 0,
        "show_id": 1636,
        "still_path": null,
        "vote_average": 0,
        "vote_count": 0,
        "crew": [],
        "guest_stars": []
      },
      {
        "air_date": "2022-04-16",
        "episode_number": 138,
        "episode_type": "standard",
        "id": 3717298,
        "name": "Violent Cricket",
        "overview": "Patrocinor tenetur tam cibus avarus tolero explicabo avaritia conqueror. Delectus annus artificiose bos cicuta charisma vos cernuus coaegresco.",
        "production_code": "",
        "runtime": 59,
        "season_number": 0,
        "show_id": 1636,
        "still_path": "/zlszC3AvfEwpo180UUdYamUZkwK.jpg",
        "vote_average": 0,
        "vote_count": 0,
        "crew": [],
        "guest_stars": []
      },
      {
        "air_date": "2022-04-16",
        "episode_number": 139,
        "episode_type": "standard",
        "id": 3717299,
        "name": "Usual Lark",
        "overview": "Nemo decumbo ipsum cauda ad. Conatus volva illo aranea voluptatem eaque. Tredecim apparatus aegrotatio cunae porro dicta super asporto.",
        "production_code": "",
        "runtime": 59,
        "season_number": 0,
        "show_id": 1636,
        "still_path": "/8FM5KwNmWO3soY6WrWC5VYu5BMk.jpg",
        "vote_average": 0,
        "vote_count": 0,
        "crew": [],
        "guest_stars": []
      },
      {
        "air_date": "2022-04-23",
        "episode_number": 140,
        "episode_type": "standard",
        "id": 3717301,
        "name": "Asleep Pony",
        "overview": "Adipiscor quia incidunt solum turbo speciosus.",
        "production_code": "",
        "runtime": 59,
        "season_number": 0,
        "show_id": 1636,
        "still_path": "/qvsDsUqMTPfxJkYaRxOlEEuwJMd.jpg",
        "vote_average": 0,
        "vote_count": 0,
        "crew": [],
        "guest_stars": []
      },
      {
        "air_date": "2022-04-23",
        "episode_number": 141,
        "episode_type": "standard",
        "id": 3717302,
        "name": "Horrible Flea",
        "overview": "Deficio unde cena supplanto bis animadverto cruciamentum degero fuga.",
        "production_code": "",
        "runtime": 59,
        "season_number": 0,
        "show_id": 1636,
        "still_path": "/cUhYKLwI0NlOzl4O0psrL6HmqWD.jpg",
        "vote_average": 0,
        "vote_count": 0,
        "crew": [],
        "guest_stars": []
      },
      {
        "air_date": "2022-05-07",
        "episode_number": 142,
        "episode_type": "standard",
        "id": 3717303,
        "name": "Boring Eel",
        "overview": "Odio decretum claudeo solitudo. Dolores audacia abundans.",
        "production_code": "",
        "runtime": 59,
        "season_number": 0,
        "show_id": 1636,
        "still_path": "/hRKrRQd1QFSs6CutLYl86jPydC7.jpg",
        "vote_average": 0,
        "vote_count": 0,
        "crew": [],
        "guest_stars": []
      },
      {
        "air_date": "2022-05-07",
        "episode_number": 143,
        "episode_type": "standard",
        "id": 3717304,
        "name": "Rapid Cephalopod",
        "overview": "Barba id confido cubicularis adhuc necessitatibus tolero. Aggero arma totus sub cotidie defessus urbanus argumentum bene.",
        "production_code": "",
        "runtime": 59,
        "season_number": 0,
        "show_id": 1636,
        "still_path": "/aN8U1cZ400tZRPbb8bdmXjH8SPe.jpg",
        "vote_average": 0,
        "vote_count": 0,
        "crew": [],
        "guest_stars": []
      },
      {
        "air_date": "2022-05-21",
        "episode_number": 144,
        "episode_type": "standard",
        "id": 3754470,
        "name": "Foolish Cheetah",
        "overview": "Angustus tondeo textor.",
        "production_code": "",
        "runtime": 59,
        "season_number": 0,
        "show_id": 1636,
        "still_path": null,
        "vote_average": 0,
        "vote_count": 0,
        "crew": [],
        "guest_stars": []
      },
      {
        "air_date": "2022-05-21",
        "episode_number": 145,
        "episode_type": "standard",
        "id": 3754471,
        "name": "Judicial Koala",
        "overview": "Suspendo vae cunae capio corrumpo curriculum odit aequus conspergo.",
        "production_code": "",
        "runtime": 59,
        "season_number": 0,
        "show_id": 1636,
        "still_path": null,
        "vote_average": 0,
        "vote_count": 0,
        "crew": [],
        "guest_stars": []
      },
      {
        "air_date": "2022-05-28",
        "episode_number": 146,
        "episode_type": "standard",
        "id": 3754472,
        "name": "Known Cougar",
        "overview": "Urbs maiores terra ustilo anser. Corporis vindico curto adicio termes vir.",
        "production_code": "",
        "runtime": 59,
        "season_number": 0,
        "show_id": 1636,
        "still_path": null,
        "vote_average": 0,
        "vote_count": 0,
        "crew": [],
        "guest_stars": []
      },
      {
        "air_date": "2022-05-28",
        "episode_number": 147,
        "episode_type": "standard",
        "id": 3754473,
        "name": "Yabbering Ocelot",
        "overview": "Voluntarius copia harum ex ascisco. Autem minima conor assumenda perferendis cultellus.",
        "production_code": "",
        "runtime": 59,
        "season_number": 0,
        "show_id": 1636,
        "still_path": null,
        "vote_average": 0,
        "vote_count": 0,
        "crew": [],
        "guest_stars": []
      },
      {
        "air_date": "1994-01-04",
        "episode_number": 148,
        "episode_type": "standard",
        "id": 4163967,
        "name": "Spotless Aphid",
        "overview": "Crebro nulla sed venio vae verbum desipio.",
        "production_code": "",
        "runtime": null,
        "season_number": 0,
        "show_id": 1636,
        "still_path": null,
        "vote_average": 0,
        "vote_count": 0,
        "crew": [],
        "guest_stars": []
      },
      {
        "air_date": null,
        "episode_number": 149,
        "episode_type": "standard",
        "id": 4972333,
        "name": "Moaning Catfish",
        "overview": "",
        "production_code": "",
        "runtime": null,
        "season_number": 0,
        "show_id": 1636,
        "still_path": null,
        "vote_average": 0,
        "vote_count": 0,
        "crew": [],
        "guest_stars": []
      },
      {
        "air_date": null,
        "episode_number": 150,
        "episode_type": "standard",
        "id": 4972356,
        "name": "Odd Jellyfish",
        "overview": "",
        "production_code": "",
        "runtime": null,
        "season_number": 0,
        "show_id": 1636,
        "still_path": null,
        "vote_average": 0,
        "vote_count": 0,
        "crew": [],
        "guest_stars": []
      },
      {
        "air_date": null,
        "episode_number": 151,
        "episode_type": "standard",
        "id": 4972357,
        "name": "Immediate Crow",
        "overview": "",
        "production_code": "",
        "runtime": null,
        "season_number": 0,
        "show_id": 1636,
        "still_path": null,
        "vote_average": 0,
        "vote_count": 0,
        "crew": [],
        "guest_stars": []
      },
      {
        "air_date": "2024-12-27",
        "episode_number": 152,
        "episode_type": "standard",
        "id": 6213755,
        "name": "Annoyed Jay",
        "overview": "Totidem aro nulla ait consequuntur adulescens.",
        "production_code": "",
        "runtime": 59,
        "season_number": 0,
        "show_id": 1636,
        "still_path": null,
        "vote_average": 0,
        "vote_count": 0,
        "crew": [],
        "guest_stars": []
      },
      {
        "air_date": "1998-11-05",
        "episode_number": 163,
        "episode_type": "standard",
        "id": 4742818,
        "name": "Primitive Cephalopod",
        "overview": "Carus titulus impedit voluntarius denuo. Pecto atqui tolero subseco viduo depulso conturbo.",
        "production_code": "m0016dtd",
        "runtime": 29,
        "season_number": 0,
        "show_id": 1636,
        "still_path": "/9Eoxdpi6eGIrPk8YBuN8PNVzvTF.jpg",
        "vote_average": 0,
        "vote_count": 0,
        "crew": [],
        "guest_stars": []
      },
      {
        "air_date": "1998-10-28",
        "episode_number": 164,
        "episode_type": "standard",
        "id": 4742817,
        "name": "Vivid Amphibian",
        "overview": "Consequatur rem trado careo esse. Explicabo thesis trans corrigo celebrer adinventitias absorbeo adulatio vinitor. Animadverto deinde appello decimus caterva valetudo audacia excepturi.",
        "production_code": "m0016mdc",
        "runtime": 28,
        "season_number": 0,
        "show_id": 1636,
        "still_path": "/x8MLcDQp7jg9PirgfvAucgj7r1m.jpg",
        "vote_average": 0,
        "vote_count": 0,
        "crew": [],
        "guest_stars": []
      },
      {
        "air_date": null,
        "episode_number": 165,
        "episode_type": "standard",
        "id": 4972338,
        "name": "Voiceless Salamander",
        "overview": "",
        "production_code": "",
        "runtime": null,
        "season_number": 0,
        "show_id": 1636,
        "still_path": null,
        "vote_average": 0,
        "vote_count": 0,
        "crew": [],
        "guest_stars": []
      },
      {
        "air_date": null,
        "episode_number": 166,
        "episode_type": "standard",
        "id": 4972339,
        "name": "Clever Peafowl",
        "overview": "",
        "production_code": "",
        "runtime": null,
        "season_number": 0,
        "show_id": 1636,
        "still_path": null,
        "vote_average": 0,
        "vote_count": 0,
        "crew": [],
        "guest_stars": []
      },
      {
        "air_date": null,
        "episode_number": 167,
        "episode_type": "standard",
        "id": 4972348,
        "name": "Blushing Koala",
        "overview": "",
        "production_code": "",
        "runtime": null,
        "season_number": 0,
        "show_id": 1636,
        "still_path": null,
        "vote_average": 0,
        "vote_count": 0,
        "crew": [],
        "guest_stars": []
      },
      {
        "air_date": null,
        "episode_number": 168,
        "episode_type": "standard",
        "id": 4972350,
        "name": "Retired Yak",
        "overview": "",
        "production_code": "",
        "runtime": null,
        "season_number": 0,
        "show_id": 1636,
        "still_path": null,
        "vote_average": 0,
        "vote_count": 0,
        "crew": [],
        "guest_stars": []
      },
      {
        "air_date": null,
        "episode_number": 169,
        "episode_type": "standard",
        "id": 4972352,
        "name": "Slow Ape",
        "overview": "",
        "production_code": "",
        "runtime": null,
        "season_number": 0,
        "show_id": 1636,
        "still_path": null,
        "vote_average": 0,
        "vote_count": 0,
        "crew": [],
        "guest_stars": []
      },
      {
        "air_date": null,
        "episode_number": 170,
        "episode_type": "standard",
        "id": 4972353,
        "name": "Marine Clownfish",
        "overview": "",
        "production_code": "",
        "runtime": null,
        "season_number": 0,
        "show_id": 1636,
        "still_path": null,
        "vote_average": 0,
        "vote_count": 0,
        "crew": [],
        "guest_stars": []
      },
      {
        "air_date": null,
        "episode_number": 171,
        "episode_type": "standard",
        "id": 4972354,
        "name": "Famous Condor",
        "overview": "",
        "production_code": "",
        "runtime": null,
        "season_number": 0,
        "show_id": 1636,
        "still_path": null,
        "vote_average": 0,
        "vote_count": 0,
        "crew": [],
        "guest_stars": []
      },
      {
        "air_date": null,
        "episode_number": 172,
        "episode_type": "standard",
        "id": 4972355,
        "name": "Intelligent Puffin",
        "overview": "",
        "production_code": "",
        "runtime": null,
        "season_number": 0,
        "show_id": 1636,
        "still_path": null,
        "vote_average": 0,
        "vote_count": 0,
        "crew": [],
        "guest_stars": []
      },
      {
        "air_date": "2000-05-29",
        "episode_number": 173,
        "episode_type": "standard",
        "id": 5728989,
        "name": "Secure Hippopotamus",
        "overview": "",
        "production_code": "",
        "runtime": null,
        "season_number": 0,
        "show_id": 1636,
        "still_path": null,
        "vote_average": 0,
        "vote_count": 0,
        "crew": [],
        "guest_stars": [
          {
            "character": "Self - Host",
            "credit_id": "658c2daab339032202e848e9",
            "order": 2,
            "adult": false,
            "gender": 2,
            "id": 1216381,
            "known_for_department": "Acting",
            "name": "Patricia Kuhn",
            "original_name": "Patricia Kuhn",
            "popularity": 0.3996,
            "profile_path": "/zI1k51SZectygJpkDXtLc0FxG2V.jpg"
          },
          {
            "character": "Self - Host",
            "credit_id": "658c3141e2102301491fabac",
            "order": 24,
            "adult": false,
            "gender": 2,
            "id": 207302,
            "known_for_department": "Acting",
            "name": "Mr. Troy Satterfield",
            "original_name": "Mr. Troy Satterfield",
            "popularity": 1.296,
            "profile_path": "/hvRZoksrBZ4Bhy4tj10RjxhQLhW.jpg"
          }
        ]
      },
      {
        "air_date": "2000-12-24",
        "episode_number": 174,
        "episode_type": "standard",
        "id": 5728992,
        "name": "Poor Takin",
        "overview": "",
        "production_code": "",
        "runtime": null,
        "season_number": 0,
        "show_id": 1636,
        "still_path": null,
        "vote_average": 0,
        "vote_count": 0,
        "crew": [],
        "guest_stars": [
          {
            "character": "Self - Host",
            "credit_id": "6729f7e1425bdcd2ace32ad0",
            "order": 946,
            "adult": false,
            "gender": 0,
            "id": 3834424,
            "known_for_department": "Acting",
            "name": "Josephine Quitzon V",
            "original_name": "Josephine Quitzon V",
            "popularity": 0.0976,
            "profile_path": null
          }
        ]
      },
      {
        "air_date": "2001-08-09",
        "episode_number": 175,
        "episode_type": "standard",
        "id": 5728993,
        "name": "Evil Marmoset",
        "overview": "",
        "production_code": "",
        "runtime": null,
        "season_number": 0,
        "show_id": 1636,
        "still_path": null,
        "vote_average": 0,
        "vote_count": 0,
        "crew": [],
        "guest_stars": [
          {
            "character": "Self - Host",
            "credit_id": "6729f8ad599da289809524b2",
            "order": 948,
            "adult": false,
            "gender": 1,
            "id": 1037368,
            "known_for_department": "Acting",
            "name": "Isaac Douglas",
            "original_name": "Isaac Douglas",
            "popularity": 1.4053,
            "profile_path": "/dvV48vgRxvtBDzA6dYLPuaCoULV.jpg"
          }
        ]
      },
      {
        "air_date": "2006-12-25",
        "episode_number": 176,
        "episode_type": "standard",
        "id": 5733234,
        "name": "Dependent Sailfish",
        "overview": "",
        "production_code": "",
        "runtime": null,
        "season_number": 0,
        "show_id": 1636,
        "still_path": null,
        "vote_average": 0,
        "vote_count": 0,
        "crew": [],
        "guest_stars": [
          {
            "character": "Self - Host",
            "credit_id": "658c30e5e18e3f7b01f9c580",
            "order": 3,
            "adult": false,
            "gender": 1,
            "id": 1216060,
            "known_for_department": "Acting",
            "name": "Nick Deckow",
            "original_name": "Nick Deckow",
            "popularity": 1.4489,
            "profile_path": "/vmmNALj0tR9ZzmV8FmykQ00QnxF.jpg"
          },
          {
            "character": "Self - Host",
            "credit_id": "658c30faae3668742ebf94e9",
            "order": 4,
            "adult": false,
            "gender": 2,
            "id": 149993,
            "known_for_department": "Acting",
            "name": "Ed Kling MD",
            "original_name": "Ed Kling MD",
            "popularity": 1.4727,
            "profile_path": "/eO5SQzSRcdfz0bdF8CtVyMnxhrg.jpg"
          },
          {
            "character": "Self - Host",
            "credit_id": "658c31ede2102302ef1f8112",
            "order": 5,
            "adult": false,
            "gender": 1,
            "id": 1131183,
            "known_for_department": "Acting",
            "name": "Lorena Schowalter",
            "original_name": "Lorena Schowalter",
            "popularity": 0.7602,
            "profile_path": "/iccnca4C9YqWM8zUWQljIsf07qV.jpg"
          }
        ]
      },
      {
        "air_date": "2007-12-25",
        "episode_number": 177,
        "episode_type": "standard",
        "id": 5733236,
        "name": "Elderly Coyote",
        "overview": "",
        "production_code": "",
        "runtime": null,
        "season_number": 0,
        "show_id": 1636,
        "still_path": null,
        "vote_average": 0,
        "vote_count": 0,
        "crew": [],
        "guest_stars": []
      },
      {
        "air_date": "2007-12-25",
        "episode_number": 178,
        "episode_type": "standard",
        "id": 5733238,
        "name": "Close Prawn",
        "overview": "",
        "production_code": "",
        "runtime": null,
        "season_number": 0,
        "show_id": 1636,
        "still_path": null,
        "vote_average": 0,
        "vote_count": 0,
        "crew": [],
        "guest_stars": []
      }
    ],
    "name": "Specials",
    "overview": "",
    "id": 4523,
    "poster_path": null,
    "season_number": 0,
    "vote_average": 0
  }
}
