{
  "headers": {
    "age": "314",
    "alt-svc": "h3=\":443\"; ma=86400",
    "cache-control": "public, max-age=22441",
    "content-type": "application/json;charset=utf-8",
    "etag": "W/\"62ca76e67276976f2f0d56c36be59177\"",
    "server": "openresty",
    "vary": "accept-encoding, Origin",
    "via": "1.1 0a71d283a25c1e3f082b4dbc9d844dfe.cloudfront.net (CloudFront)",
    "x-amz-cf-id": "c-_FT_lKsIG6kitULNhev-XRNFKj2nQP-_CLLYIYgIQ3odzYnGWUqg==",
    "x-amz-cf-pop": "FRA60-P3",
    "x-az": "us-east-1c",
    "x-cache": "Hit from cloudfront",
    "x-memc": "HIT",
    "x-memc-age": "2809",
    "x-memc-expires": "22441",
    "x-memc-key": "ef9fc34187f08091130bb02c96caed3d",
    "x-task-id": "e78ad5e342f040ccaf3804ad02ab4916"
  },
  "data": {
    "_id": "525729f5760ee3776a2c0d67",
    "air_date": "1998-03-09",
    "episodes": [
      {
        "air_date": "1998-03-09",
        "episode_number": 1,
        "episode_type": "standard",
        "id": 158557,
        "name": "Easy Pig",
        "overview": "",
        "production_code": "",
        "runtime": null,
        "season_number": 3,
        "show_id": 2224,
        "still_path": null,
        "vote_average": 5,
        "vote_count": 1,
        "crew": [],
        "guest_stars": []
      },
      {
        "air_date": "1998-03-10",
        "episode_number": 2,
        "episode_type": "standard",
        "id": 158558,
        "name": "Healthy Felidae",
        "overview": "",
        "production_code": "",
        "runtime": null,
        "season_number": 3,
        "show_id": 2224,
        "still_path": null,
        "vote_average": 7,
        "vote_count": 1,
        "crew": [],
        "guest_stars": []
      },
      {
        "air_date": "1998-03-11",
        "episode_number": 3,
        "episode_type": "standard",
        "id": 158559,
        "name": "Genetic Impala",
        "overview": "",
        "production_code": "",
        "runtime": null,
        "season_number": 3,
        "show_id": 2224,
        "still_path": null,
        "vote_average": 5,
        "vote_count": 1,
        "crew": [],
        "guest_stars": []
      },
      {
        "air_date": "1998-03-12",
        "episode_number": 4,
        "episode_type": "standard",
        "id": 158560,
        "name": "Functional Anteater",
        "overview": "",
        "production_code": "",
        "runtime": null,
        "season_number": 3,
        "show_id": 2224,
        "still_path": null,
        "vote_average": 5,
        "vote_count": 1,
        "crew": [],
        "guest_stars": []
      },
      {
        "air_date": "1998-03-30",
        "episode_number": 5,
        "episode_type": "standard",
        "id": 158570,
        "name": "Chilly Pigeon",
        "overview": "",
        "production_code": "",
        "runtime": null,
        "season_number": 3,
        "show_id": 2224,
        "still_path": null,
        "vote_average": 5,
        "vote_count": 1,
        "crew": [],
        "guest_stars": []
      },
      {
        "air_date": "1998-06-03",
        "episode_number": 6,
        "episode_type": "standard",
        "id": 158571,
        "name": "Theoretical Smelt",
        "overview": "",
        "production_code": "",
        "runtime": null,
        "season_number": 3,
        "show_id": 2224,
        "still_path": null,
        "vote_average": 5,
        "vote_count": 1,
        "crew": [],
        "guest_stars": []
      },
      {
        "air_date": "1998-06-25",
        "episode_number": 7,
        "episode_type": "standard",
        "id": 158572,
        "name": "Historic Halibut",
        "overview": "",
        "production_code": "",
        "runtime": null,
        "season_number": 3,
        "show_id": 2224,
        "still_path": null,
        "vote_average": 6,
        "vote_count": 1,
        "crew": [],
        "guest_stars": []
      },
      {
        "air_date": "1998-09-10",
        "episode_number": 8,
        "episode_type": "standard",
        "id": 158561,
        "name": "Dependent Gerbil",
        "overview": "",
        "production_code": "",
        "runtime": null,
        "season_number": 3,
        "show_id": 2224,
        "still_path": null,
        "vote_average": 5,
        "vote_count": 1,
        "crew": [],
        "guest_stars": []
      },
      {
        "air_date": "1998-09-14",
        "episode_number": 9,
        "episode_type": "standard",
        "id": 158573,
        "name": "Big Capybara",
        "overview": "",
        "production_code": "",
        "runtime": null,
        "season_number": 3,
        "show_id": 2224,
        "still_path": null,
        "vote_average": 5,
        "vote_count": 1,
        "crew": [],
        "guest_stars": []
      },
      {
        "air_date": "1998-09-15",
        "episode_number": 10,
        "episode_type": "standard",
        "id": 158562,
        "name": "Icy Gopher",
        "overview": "",
        "production_code": "",
        "runtime": null,
        "season_number": 3,
        "show_id": 2224,
        "still_path": null,
        "vote_average": 6,
        "vote_count": 1,
        "crew": [],
        "guest_stars": []
      },
      {
        "air_date": "1998-09-16",
        "episode_number": 11,
        "episode_type": "standard",
        "id": 158563,
        "name": "Clear Deer",
        "overview": "",
        "production_code": "",
        "runtime": null,
        "season_number": 3,
        "show_id": 2224,
        "still_path": null,
        "vote_average": 5,
        "vote_count": 1,
        "crew": [],
        "guest_stars": []
      },
      {
        "air_date": "1998-09-17",
        "episode_number": 12,
        "episode_type": "standard",
        "id": 158564,
        "name": "Statistical Anglerfish",
        "overview": "",
        "production_code": "",
        "runtime": null,
        "season_number": 3,
        "show_id": 2224,
        "still_path": null,
        "vote_average": 6,
        "vote_count": 1,
        "crew": [],
        "guest_stars": []
      },
      {
        "air_date": "1998-09-21",
        "episode_number": 13,
        "episode_type": "standard",
        "id": 158565,
        "name": "General Tuna",
        "overview": "",
        "production_code": "",
        "runtime": null,
        "season_number": 3,
        "show_id": 2224,
        "still_path": null,
        "vote_average": 9,
        "vote_count": 1,
        "crew": [],
        "guest_stars": []
      },
      {
        "air_date": "1998-09-22",
        "episode_number": 14,
        "episode_type": "standard",
        "id": 158566,
        "name": "Blonde Marmoset",
        "overview": "",
        "production_code": "",
        "runtime": null,
        "season_number": 3,
        "show_id": 2224,
        "still_path": null,
        "vote_average": 5,
        "vote_count": 1,
        "crew": [],
        "guest_stars": []
      },
      {
        "air_date": "1998-09-23",
        "episode_number": 15,
        "episode_type": "standard",
        "id": 158567,
        "name": "Obedient Guineafowl",
        "overview": "",
        "production_code": "",
        "runtime": null,
        "season_number": 3,
        "show_id": 2224,
        "still_path": null,
        "vote_average": 6,
        "vote_count": 1,
        "crew": [],
        "guest_stars": []
      },
      {
        "air_date": "1998-09-24",
        "episode_number": 16,
        "episode_type": "standard",
        "id": 158568,
        "name": "Faithful Eel",
        "overview": "",
        "production_code": "",
        "runtime": null,
        "season_number": 3,
        "show_id": 2224,
        "still_path": null,
        "vote_average": 5,
        "vote_count": 1,
        "crew": [],
        "guest_stars": []
      },
      {
        "air_date": "1998-10-27",
        "episode_number": 17,
        "episode_type": "standard",
        "id": 158580,
        "name": "Mutual Owl",
        "overview": "",
        "production_code": "",
        "runtime": null,
        "season_number": 3,
        "show_id": 2224,
        "still_path": null,
        "vote_average": 6,
        "vote_count": 1,
        "crew": [],
        "guest_stars": []
      },
      {
        "air_date": "1998-11-02",
        "episode_number": 18,
        "episode_type": "standard",
        "id": 158569,
        "name": "Institutional Trout",
        "overview": "",
        "production_code": "",
        "runtime": null,
        "season_number": 3,
        "show_id": 2224,
        "still_path": null,
        "vote_average": 5,
        "vote_count": 1,
        "crew": [],
        "guest_stars": []
      },
      {
        "air_date": "1998-11-03",
        "episode_number": 19,
        "episode_type": "standard",
        "id": 158581,
        "name": "Invisible Cockroach",
        "overview": "",
        "production_code": "",
        "runtime": null,
        "season_number": 3,
        "show_id": 2224,
        "still_path": null,
        "vote_average": 5,
        "vote_count": 1,
        "crew": [],
        "guest_stars": []
      },
      {
        "air_date": "1998-11-04",
        "episode_number": 20,
        "episode_type": "standard",
        "id": 158582,
        "name": "Grumpy Beaver",
        "overview": "",
        "production_code": "",
        "runtime": null,
        "season_number": 3,
        "show_id": 2224,
        "still_path": null,
        "vote_average": 4,
        "vote_count": 1,
        "crew": [],
        "guest_stars": []
      },
      {
        "air_date": "1998-11-05",
        "episode_number": 21,
        "episode_type": "standard",
        "id": 158583,
        "name": "Entire Xerinae",
        "overview": "",
        "production_code": "",
        "runtime": null,
        "season_number": 3,
        "show_id": 2224,
        "still_path": null,
        "vote_average": 5,
        "vote_count": 1,
        "crew": [],
        "guest_stars": []
      },
      {
        "air_date": "1998-11-09",
        "episode_number": 22,
        "episode_type": "standard",
        "id": 158584,
        "name": "Yielding Opossum",
        "overview": "",
        "production_code": "",
        "runtime": null,
        "season_number": 3,
        "show_id": 2224,
        "still_path": null,
        "vote_average": 5,
        "vote_count": 1,
        "crew": [],
        "guest_stars": []
      },
      {
        "air_date": "1998-11-10",
        "episode_number": 23,
        "episode_type": "standard",
        "id": 158585,
        "name": "Disciplinary Seahorse",
        "overview": "",
        "production_code": "",
        "runtime": null,
        "season_number": 3,
        "show_id": 2224,
        "still_path": null,
        "vote_average": 5,
        "vote_count": 1,
        "crew": [],
        "guest_stars": []
      },
      {
        "air_date": "1998-11-11",
        "episode_number": 24,
        "episode_type": "standard",
        "id": 158586,
        "name": "Tiny Ocelot",
        "overview": "",
        "production_code": "",
        "runtime": null,
        "season_number": 3,
        "show_id": 2224,
        "still_path": null,
        "vote_average": 5,
        "vote_count": 1,
        "crew": [],
        "guest_stars": []
      },
      {
        "air_date": "1998-11-16",
        "episode_number": 25,
        "episode_type": "standard",
        "id": 158587,
        "name": "Gradual Coyote",
        "overview": "",
        "production_code": "",
        "runtime": null,
        "season_number": 3,
        "show_id": 2224,
        "still_path": null,
        "vote_average": 5,
        "vote_count": 1,
        "crew": [],
        "guest_stars": []
      },
      {
        "air_date": "1998-11-17",
        "episode_number": 26,
        "episode_type": "standard",
        "id": 158574,
        "name": "Residential Fly",
        "overview": "",
        "production_code": "",
        "runtime": null,
        "season_number": 3,
        "show_id": 2224,
        "still_path": null,
        "vote_average": 6,
        "vote_count": 1,
        "crew": [],
        "guest_stars": []
      },
      {
        "air_date": "1998-11-18",
        "episode_number": 27,
        "episode_type": "standard",
        "id": 158576,
        "name": "Forthcoming Muskox",
        "overview": "",
        "production_code": "",
        "runtime": null,
        "season_number": 3,
        "show_id": 2224,
        "still_path": null,
        "vote_average": 1,
        "vote_count": 1,
        "crew": [],
        "guest_stars": []
      },
      {
        "air_date": "1998-11-19",
        "episode_number": 28,
        "episode_type": "standard",
        "id": 158575,
        "name": "Direct Pony",
        "overview": "",
        "production_code": "",
        "runtime": null,
        "season_number": 3,
        "show_id": 2224,
        "still_path": null,
        "vote_average": 2,
        "vote_count": 1,
        "crew": [],
        "guest_stars": [
          {
            "character": "Self",
            "credit_id": "5bba5b230e0a2634e60312dd",
            "order": 1162,
            "adult": false,
            "gender": 2,
            "id": 94743,
            "known_for_department": "Acting",
            "name": "Eleanor Wilkinson",
            "original_name": "Eleanor Wilkinson",
            "popularity": 3.2564,
            "profile_path": "/oz5L8n5aPc2WzRbehkb01BxtKKv.jpg"
          }
        ]
      },
      {
        "air_date": "1998-12-14",
        "episode_number": 29,
        "episode_type": "standard",
        "id": 158577,
        "name": "Passing Hummingbird",
        "overview": "",
        "production_code": "",
        "runtime": null,
        "season_number": 3,
        "show_id": 2224,
        "still_path": null,
        "vote_average": 5,
        "vote_count": 1,
        "crew": [],
        "guest_stars": [
          {
            "character": "Self",
            "credit_id": "5bba5b2f0e0a2634f90331cc",
            "order": 1165,
            "adult": false,
            "gender": 1,
            "id": 61980,
            "known_for_department": "Acting",
            "name": "Kim Emmerich MD",
            "original_name": "Kim Emmerich MD",
            "popularity": 3.4471,
            "profile_path": "/4yDh5iu4Qyib35aXfo7SStFpnNC.jpg"
          }
        ]
      },
      {
        "air_date": "1998-12-15",
        "episode_number": 30,
        "episode_type": "standard",
        "id": 158578,
        "name": "Electronic Cod",
        "overview": "",
        "production_code": "",
        "runtime": null,
        "season_number": 3,
        "show_id": 2224,
        "still_path": null,
        "vote_average": 5,
        "vote_count": 1,
        "crew": [],
        "guest_stars": [
          {
            "character": "Self",
            "credit_id": "5bba5b3a0e0a2634e6031313",
            "order": 1168,
            "adult": false,
            "gender": 0,
            "id": 1215507,
            "known_for_department": "Acting",
            "name": "Lorenzo Pagac",
            "original_name": "Lorenzo Pagac",
            "popularity": 0.8563,
            "profile_path": "/fyIOEsyk6Wz31ApaDCMpTx4Va3Z.jpg"
          }
        ]
      },
      {
        "air_date": "1998-12-16",
        "episode_number": 31,
        "episode_type": "standard",
        "id": 158579,
        "name": "Interim Pigeon",
        "overview": "",
        "production_code": "",
        "runtime": null,
        "season_number": 3,
        "show_id": 2224,
        "still_path": null,
        "vote_average": 9,
        "vote_count": 1,
        "crew": [],
        "guest_stars": []
      },
      {
        "air_date": "1998-12-17",
        "episode_number": 32,
        "episode_type": "standard",
        "id": 158556,
        "name": "Obliged Rodent",
        "overview": "Absorbeo communis ventus abduco valetudo degusto nemo valeo.",
        "production_code": "",
        "runtime": null,
        "season_number": 3,
        "show_id": 2224,
        "still_path": null,
        "vote_average": 5,
        "vote_count": 1,
        "crew": [],
        "guest_stars": [
          {
            "character": "Self",
            "credit_id": "525729f7760ee3776a2c1053",
            "order": 502,
            "adult": false,
            "gender": 2,
            "id": 15860,
            "known_for_department": "Acting",
            "name": "Darryl Muller",
            "original_name": "Darryl Muller",
            "popularity": 3.1437,
            "profile_path": "/n6VZ8OQmozHmnJQRwR55gBH8Tl0.jpg"
          },
          {
            "character": "Self",
            "credit_id": "52572a0d760ee3776a2c3d25",
            "order": 1170,
            "adult": false,
            "gender": 2,
            "id": 6105,
            "known_for_department": "Acting",
            "name": "Jon Gleichner",
            "original_name": "Jon Gleichner",
            "popularity": 3.6651,
            "profile_path": "/xUiYIhzC0HfpkWn5QuaICLtE6Hy.jpg"
          }
        ]
      },
      {
        "air_date": "1998-07-22",
        "episode_number": 34,
        "episode_type": "finale",
        "id": 158588,
        "name": "Favourable Toucan",
        "overview": "",
        "production_code": "",
        "runtime": null,
        "season_number": 3,
        "show_id": 2224,
        "still_path": null,
        "vote_average": 5,
        "vote_count": 1,
        "crew": [],
        "guest_stars": []
      }
    ],
    "name": "Season 3",
    "overview": "",
    "id": 6855,
    "poster_path": "/jXrc4QyW1berVN4ZaX2eX0jOPsq.jpg",
    "season_number": 3,
    "vote_average": 5.2
  }
}
